{
  "artifact_id": "fsch_0502f72072be44d1975c83fe2b657491",
  "artifact_kind": "family_scheme",
  "content_hash": "sha256:0b948d54fd9733c8ba21dc3be45d62970e7ad6d5ac177c0cfea74d7b775206c7",
  "created_at": "2026-07-23T12:07:34.886335Z",
  "extensions": {},
  "payload": {
    "description": "Groups identical structural queries with identical parameter bindings and origin.",
    "dimensions": [
      "query.shape",
      "parameters.binding",
      "origin.frame"
    ],
    "family_scheme_key": "exact-execution.v1",
    "missing_value_policy": "preserve_unknown",
    "title": "Exact execution"
  },
  "producer": {
    "build": "milestone-d-seed",
    "name": "planguard",
    "version": "0.4.0"
  },
  "provenance": {
    "code_revision": null,
    "configuration_ref": null,
    "derivation_key": null,
    "input_refs": [],
    "notes": []
  },
  "schema_version": "planguard.family-scheme.v1"
}
