{
  "artifact_id": "sci_5edb6431d243e2a890ccbac967410bf4",
  "artifact_kind": "scenario_instance",
  "content_hash": "sha256:b7e4396236551e0b372f3652f03a167959b40e061a067ce69f503d258c2123c0",
  "created_at": "1970-01-01T00:00:00Z",
  "extensions": {},
  "payload": {
    "applied_mutations": [],
    "binding_ref": {
      "artifact_id": "scb_d65c26c156b489b748223b6a377e136d",
      "artifact_kind": "scenario_binding",
      "content_hash": "sha256:e8cd0135d8e9c128b7a2a671b7f4088021292686e44cb25977a3d9836be5bd31",
      "schema_version": "planguard.scenario-binding.v1"
    },
    "composed_from_refs": [],
    "expected_capabilities": [],
    "parameter_bindings": {
      "batch_size": 6,
      "page_offset": 250,
      "parent_count": 6,
      "relation_fanout": 6,
      "scale_profile": "tiny",
      "tenant_skew": "uniform",
      "transaction_scope": "autocommit"
    },
    "projected_dimensions": [],
    "seed": 4021,
    "series_key": null,
    "tags": [
      "milestone-d",
      "academic-lab",
      "representative"
    ],
    "template_ref": {
      "artifact_id": "sct_70fb1da2591642cc288d9fb2106543a3",
      "artifact_kind": "scenario_template",
      "content_hash": "sha256:ebd74d8bebbc80e99490fbd2bdd1b18fe234deeb1d41a0332350ea1a90377dff",
      "schema_version": "planguard.scenario-template.v1"
    },
    "variant_key": "optimized"
  },
  "producer": {
    "build": "milestone-d-seed",
    "name": "planguard",
    "version": "0.4.0"
  },
  "provenance": {
    "code_revision": null,
    "configuration_ref": null,
    "derivation_key": "scenario-instantiate.v1",
    "input_refs": [
      {
        "artifact_id": "sct_70fb1da2591642cc288d9fb2106543a3",
        "artifact_kind": "scenario_template",
        "content_hash": "sha256:ebd74d8bebbc80e99490fbd2bdd1b18fe234deeb1d41a0332350ea1a90377dff",
        "schema_version": "planguard.scenario-template.v1"
      },
      {
        "artifact_id": "scb_d65c26c156b489b748223b6a377e136d",
        "artifact_kind": "scenario_binding",
        "content_hash": "sha256:e8cd0135d8e9c128b7a2a671b7f4088021292686e44cb25977a3d9836be5bd31",
        "schema_version": "planguard.scenario-binding.v1"
      }
    ],
    "notes": []
  },
  "schema_version": "planguard.scenario-instance.v1"
}
